helloworldagain.py
helloworld_boyan_20210805-0.0.2.dist-info/LICENCE.txt
helloworld_boyan_20210805-0.0.2.dist-info/METADATA
helloworld_boyan_20210805-0.0.2.dist-info/WHEEL
helloworld_boyan_20210805-0.0.2.dist-info/top_level.txt
helloworld_boyan_20210805-0.0.2.dist-info/RECORD
